{"assets/images/background.jpg":["assets/images/background.jpg"],"assets/images/control%20panel.png":["assets/images/control%20panel.png"],"assets/images/customize.png":["assets/images/customize.png"],"assets/images/folder.png":["assets/images/folder.png"],"assets/images/music_background.jpg":["assets/images/music_background.jpg"],"assets/images/pictures/picture1.jpg":["assets/images/pictures/picture1.jpg"],"assets/images/pictures/picture2.jpg":["assets/images/pictures/picture2.jpg"],"assets/images/pictures/picture3.jpg":["assets/images/pictures/picture3.jpg"],"assets/images/pictures/picture4.jpg":["assets/images/pictures/picture4.jpg"],"assets/images/pictures/picture5.jpg":["assets/images/pictures/picture5.jpg"],"assets/images/profile.jpeg":["assets/images/profile.jpeg"],"assets/images/run.png":["assets/images/run.png"],"assets/images/start%20menu.png":["assets/images/start%20menu.png"],"packages/cupertino_icons/assets/CupertinoIcons.ttf":["packages/cupertino_icons/assets/CupertinoIcons.ttf"]}